{"cameraMode":{"drawMode":0,"name":"Shaded","section":"Shading Mode"},"sceneLighting":false,"audioPlay":false,"sceneViewState":{"showFog":true,"showMaterialUpdate":false,"showSkybox":false,"showFlares":true,"showImageEffects":true,"showParticleSystems":true,"showVisualEffectGraphs":true,"m_FxEnabled":true},"in2DMode":false,"pivot":{"x":0.0,"y":-0.3049999475479126,"z":0.0},"rotation":{"x":-0.17434696853160859,"y":0.4410707652568817,"z":-0.08787781000137329,"w":-0.8759876489639282},"size":1.2541532516479493,"orthographic":true}